ArabicTextNormalzation/ArabicTextNormalzation.py
ArabicTextNormalzation/__init__.py
ArabicTextNormalzation-0.0.3.dist-info/LICENSE
ArabicTextNormalzation-0.0.3.dist-info/METADATA
ArabicTextNormalzation-0.0.3.dist-info/WHEEL
ArabicTextNormalzation-0.0.3.dist-info/top_level.txt
ArabicTextNormalzation-0.0.3.dist-info/RECORD
