Metadata-Version: 2.1
Name: ArabicTextNormalzation
Version: 0.0.3
Summary: ArabicTextNormalzation
Author: Yousif Ahmed Alhaj
Author-email: yalhag@gmail.com
Keywords: python,Arabic text preprocessing,Arabic text classification,Arabic text Normalization,Arabic sentiment ana;ysis
Classifier: Development Status :: 1 - Planning
Classifier: Intended Audience :: Developers
Classifier: Programming Language :: Python :: 3
Classifier: Operating System :: Unix
Classifier: Operating System :: MacOS :: MacOS X
Classifier: Operating System :: Microsoft :: Windows
License-File: LICENSE
